<?xml version="1.0" encoding="UTF-8"?>
<!DOCTYPE plist PUBLIC "-//Apple//DTD PLIST 1.0//EN" "http://www.apple.com/DTDs/PropertyList-1.0.dtd"/>

<plist version="1.0">
    <dict>
        <key>ROOT</key>
        <array>
            <dict>
                <key>id</key>
                <string>151</string>
                <key>className</key>
                <string>PTModelAssetObstacle</string>
                <key>Name</key>
                <dict>
                    <key>value</key>
                    <string>GoalTrigger</string>
                </dict>
                <key>Collision Shape</key>
                <dict>
                    <key>id</key>
                    <string>2386</string>
                    <key>className</key>
                    <string>PTModelPolygon</string>
                    <key>Name</key>
                    <dict>
                        <key>value</key>
                        <string></string>
                    </dict>
                    <key>points</key>
                    <array>
                        <string>{-25.000000,-25.000000}</string>
                        <string>{25.000000,-25.000000}</string>
                        <string>{25.000000,25.000000}</string>
                        <string>{-25.000000,25.000000}</string>
                    </array>
                    <key>oneWayCollisionVector</key>
                    <string>{0.000000,0.000000}</string>
                    <key>shapeType</key>
                    <string>1</string>
                </dict>
            </dict>
            <dict>
                <key>id</key>
                <string>166</string>
                <key>className</key>
                <string>PTModelAssetObstacle</string>
                <key>Name</key>
                <dict>
                    <key>value</key>
                    <string>Point</string>
                </dict>
                <key>Collision Shape</key>
                <dict>
                    <key>id</key>
                    <string>1097</string>
                    <key>className</key>
                    <string>PTModelCircle</string>
                    <key>Name</key>
                    <dict>
                        <key>value</key>
                        <string></string>
                    </dict>
                    <key>points</key>
                    <array>
                        <string>{0.000000,0.000000}</string>
                        <string>{34.799999,1.000000}</string>
                    </array>
                    <key>oneWayCollisionVector</key>
                    <string>{0.000000,0.000000}</string>
                    <key>shapeType</key>
                    <string>2</string>
                </dict>
            </dict>
            <dict>
                <key>id</key>
                <string>177</string>
                <key>className</key>
                <string>PTModelAssetObstacle</string>
                <key>Name</key>
                <dict>
                    <key>value</key>
                    <string>Puck</string>
                </dict>
                <key>Collision Shape</key>
                <dict>
                    <key>id</key>
                    <string>322</string>
                    <key>className</key>
                    <string>PTModelCircle</string>
                    <key>Name</key>
                    <dict>
                        <key>value</key>
                        <string></string>
                    </dict>
                    <key>points</key>
                    <array>
                        <string>{0.000000,0.000000}</string>
                        <string>{119.800003,6.000000}</string>
                    </array>
                    <key>oneWayCollisionVector</key>
                    <string>{0.000000,0.000000}</string>
                    <key>shapeType</key>
                    <string>2</string>
                </dict>
            </dict>
            <dict>
                <key>id</key>
                <string>273</string>
                <key>className</key>
                <string>PTModelAssetObstacle</string>
                <key>Name</key>
                <dict>
                    <key>value</key>
                    <string>backhoop</string>
                </dict>
                <key>Collision Shape</key>
                <dict>
                    <key>id</key>
                    <string>274</string>
                    <key>className</key>
                    <string>PTModelPolygon</string>
                    <key>Name</key>
                    <dict>
                        <key>value</key>
                        <string></string>
                    </dict>
                    <key>points</key>
                    <array>
                        <string>{-122.000000,-27.000000}</string>
                        <string>{122.000000,-27.000000}</string>
                        <string>{122.000000,28.000000}</string>
                        <string>{-122.000000,28.000000}</string>
                    </array>
                    <key>oneWayCollisionVector</key>
                    <string>{0.000000,0.000000}</string>
                    <key>shapeType</key>
                    <string>1</string>
                </dict>
            </dict>
            <dict>
                <key>id</key>
                <string>284</string>
                <key>className</key>
                <string>PTModelAssetObstacle</string>
                <key>Name</key>
                <dict>
                    <key>value</key>
                    <string>front hoop</string>
                </dict>
                <key>Collision Shape</key>
                <dict>
                    <key>id</key>
                    <string>285</string>
                    <key>className</key>
                    <string>PTModelPolygon</string>
                    <key>Name</key>
                    <dict>
                        <key>value</key>
                        <string></string>
                    </dict>
                    <key>points</key>
                    <array>
                        <string>{-123.000000,-33.000000}</string>
                        <string>{124.000000,-33.000000}</string>
                        <string>{124.000000,34.000000}</string>
                        <string>{-123.000000,34.000000}</string>
                    </array>
                    <key>oneWayCollisionVector</key>
                    <string>{0.000000,0.000000}</string>
                    <key>shapeType</key>
                    <string>1</string>
                </dict>
            </dict>
            <dict>
                <key>id</key>
                <string>376</string>
                <key>className</key>
                <string>PTModelAssetObstacle</string>
                <key>Name</key>
                <dict>
                    <key>value</key>
                    <string>Aimer</string>
                </dict>
                <key>Collision Shape</key>
                <dict>
                    <key>id</key>
                    <string>1107</string>
                    <key>className</key>
                    <string>PTModelPolygon</string>
                    <key>Name</key>
                    <dict>
                        <key>value</key>
                        <string></string>
                    </dict>
                    <key>points</key>
                    <array>
                        <string>{-5.000000,-100.000000}</string>
                        <string>{6.000000,-100.000000}</string>
                        <string>{5.000000,1.000000}</string>
                        <string>{-5.000000,1.000000}</string>
                    </array>
                    <key>oneWayCollisionVector</key>
                    <string>{0.000000,0.000000}</string>
                    <key>shapeType</key>
                    <string>1</string>
                </dict>
            </dict>
            <dict>
                <key>id</key>
                <string>911</string>
                <key>className</key>
                <string>PTModelAssetObstacle</string>
                <key>Name</key>
                <dict>
                    <key>value</key>
                    <string>WhiteBlock</string>
                </dict>
                <key>Collision Shape</key>
                <dict>
                    <key>id</key>
                    <string>912</string>
                    <key>className</key>
                    <string>PTModelPolygon</string>
                    <key>Name</key>
                    <dict>
                        <key>value</key>
                        <string></string>
                    </dict>
                    <key>points</key>
                    <array>
                        <string>{-120.000000,-120.000000}</string>
                        <string>{120.000000,-120.000000}</string>
                        <string>{120.000000,120.000000}</string>
                        <string>{-120.000000,120.000000}</string>
                    </array>
                    <key>oneWayCollisionVector</key>
                    <string>{0.000000,0.000000}</string>
                    <key>shapeType</key>
                    <string>1</string>
                </dict>
            </dict>
            <dict>
                <key>id</key>
                <string>1008</string>
                <key>className</key>
                <string>PTModelAssetObstacle</string>
                <key>Name</key>
                <dict>
                    <key>value</key>
                    <string>GoalGraphic</string>
                </dict>
                <key>Collision Shape</key>
                <dict>
                    <key>id</key>
                    <string>1017</string>
                    <key>className</key>
                    <string>PTModelCircle</string>
                    <key>Name</key>
                    <dict>
                        <key>value</key>
                        <string></string>
                    </dict>
                    <key>points</key>
                    <array>
                        <string>{-2.000000,1.500000}</string>
                        <string>{70.000000,18.500000}</string>
                    </array>
                    <key>oneWayCollisionVector</key>
                    <string>{0.000000,0.000000}</string>
                    <key>shapeType</key>
                    <string>2</string>
                </dict>
            </dict>
            <dict>
                <key>id</key>
                <string>1210</string>
                <key>className</key>
                <string>PTModelAssetObstacle</string>
                <key>Name</key>
                <dict>
                    <key>value</key>
                    <string>GlassBlockBlue</string>
                </dict>
                <key>Collision Shape</key>
                <dict>
                    <key>id</key>
                    <string>1365</string>
                    <key>className</key>
                    <string>PTModelPolygon</string>
                    <key>Name</key>
                    <dict>
                        <key>value</key>
                        <string></string>
                    </dict>
                    <key>points</key>
                    <array>
                        <string>{0.000000,-59.000000}</string>
                        <string>{59.000000,1.000000}</string>
                        <string>{0.000000,60.000000}</string>
                        <string>{-59.000000,1.000000}</string>
                    </array>
                    <key>oneWayCollisionVector</key>
                    <string>{0.000000,0.000000}</string>
                    <key>shapeType</key>
                    <string>1</string>
                </dict>
            </dict>
            <dict>
                <key>id</key>
                <string>1552</string>
                <key>className</key>
                <string>PTModelAssetObstacle</string>
                <key>Name</key>
                <dict>
                    <key>value</key>
                    <string>DeathBlock</string>
                </dict>
                <key>Collision Shape</key>
                <dict>
                    <key>id</key>
                    <string>1553</string>
                    <key>className</key>
                    <string>PTModelPolygon</string>
                    <key>Name</key>
                    <dict>
                        <key>value</key>
                        <string></string>
                    </dict>
                    <key>points</key>
                    <array>
                        <string>{-120.000000,-120.000000}</string>
                        <string>{120.000000,-120.000000}</string>
                        <string>{120.000000,120.000000}</string>
                        <string>{-120.000000,120.000000}</string>
                    </array>
                    <key>oneWayCollisionVector</key>
                    <string>{0.000000,0.000000}</string>
                    <key>shapeType</key>
                    <string>1</string>
                </dict>
            </dict>
            <dict>
                <key>id</key>
                <string>3223</string>
                <key>className</key>
                <string>PTModelAssetObstacle</string>
                <key>Name</key>
                <dict>
                    <key>value</key>
                    <string>WhiteCircle</string>
                </dict>
                <key>Collision Shape</key>
                <dict>
                    <key>id</key>
                    <string>3224</string>
                    <key>className</key>
                    <string>PTModelPolygon</string>
                    <key>Name</key>
                    <dict>
                        <key>value</key>
                        <string></string>
                    </dict>
                    <key>points</key>
                    <array>
                        <string>{-25.000000,-25.000000}</string>
                        <string>{25.000000,-25.000000}</string>
                        <string>{25.000000,25.000000}</string>
                        <string>{-25.000000,25.000000}</string>
                    </array>
                    <key>oneWayCollisionVector</key>
                    <string>{0.000000,0.000000}</string>
                    <key>shapeType</key>
                    <string>1</string>
                </dict>
            </dict>
            <dict>
                <key>id</key>
                <string>3294</string>
                <key>className</key>
                <string>PTModelAssetObstacle</string>
                <key>Name</key>
                <dict>
                    <key>value</key>
                    <string>BlackBlock</string>
                </dict>
                <key>Collision Shape</key>
                <dict>
                    <key>id</key>
                    <string>3295</string>
                    <key>className</key>
                    <string>PTModelPolygon</string>
                    <key>Name</key>
                    <dict>
                        <key>value</key>
                        <string></string>
                    </dict>
                    <key>points</key>
                    <array>
                        <string>{-120.000000,-120.000000}</string>
                        <string>{120.000000,-120.000000}</string>
                        <string>{120.000000,120.000000}</string>
                        <string>{-120.000000,120.000000}</string>
                    </array>
                    <key>oneWayCollisionVector</key>
                    <string>{0.000000,0.000000}</string>
                    <key>shapeType</key>
                    <string>1</string>
                </dict>
            </dict>
            <dict>
                <key>id</key>
                <string>4108</string>
                <key>className</key>
                <string>PTModelAssetObstacle</string>
                <key>Name</key>
                <dict>
                    <key>value</key>
                    <string>Goal</string>
                </dict>
                <key>Collision Shape</key>
                <dict>
                    <key>id</key>
                    <string>4135</string>
                    <key>className</key>
                    <string>PTModelCircle</string>
                    <key>Name</key>
                    <dict>
                        <key>value</key>
                        <string></string>
                    </dict>
                    <key>points</key>
                    <array>
                        <string>{0.000000,0.000000}</string>
                        <string>{62.199997,-2.000000}</string>
                    </array>
                    <key>oneWayCollisionVector</key>
                    <string>{0.000000,0.000000}</string>
                    <key>shapeType</key>
                    <string>2</string>
                </dict>
            </dict>
            <dict>
                <key>id</key>
                <string>4562</string>
                <key>className</key>
                <string>PTModelAssetObstacle</string>
                <key>Name</key>
                <dict>
                    <key>value</key>
                    <string>Platform</string>
                </dict>
                <key>Collision Shape</key>
                <dict>
                    <key>id</key>
                    <string>4563</string>
                    <key>className</key>
                    <string>PTModelPolygon</string>
                    <key>Name</key>
                    <dict>
                        <key>value</key>
                        <string></string>
                    </dict>
                    <key>points</key>
                    <array>
                        <string>{-90.000000,-20.000000}</string>
                        <string>{90.000000,-20.000000}</string>
                        <string>{90.000000,20.000000}</string>
                        <string>{-90.000000,20.000000}</string>
                    </array>
                    <key>oneWayCollisionVector</key>
                    <string>{0.000000,0.000000}</string>
                    <key>shapeType</key>
                    <string>1</string>
                </dict>
            </dict>
            <dict>
                <key>id</key>
                <string>4720</string>
                <key>className</key>
                <string>PTModelAssetObstacle</string>
                <key>Name</key>
                <dict>
                    <key>value</key>
                    <string>CheckersBG</string>
                </dict>
                <key>Collision Shape</key>
                <dict>
                    <key>id</key>
                    <string>4721</string>
                    <key>className</key>
                    <string>PTModelPolygon</string>
                    <key>Name</key>
                    <dict>
                        <key>value</key>
                        <string></string>
                    </dict>
                    <key>points</key>
                    <array>
                        <string>{-256.000000,-512.000000}</string>
                        <string>{256.000000,-512.000000}</string>
                        <string>{256.000000,512.000000}</string>
                        <string>{-256.000000,512.000000}</string>
                    </array>
                    <key>oneWayCollisionVector</key>
                    <string>{0.000000,0.000000}</string>
                    <key>shapeType</key>
                    <string>1</string>
                </dict>
            </dict>
            <dict>
                <key>id</key>
                <string>4786</string>
                <key>className</key>
                <string>PTModelAssetObstacle</string>
                <key>Name</key>
                <dict>
                    <key>value</key>
                    <string>CheckersBG2</string>
                </dict>
                <key>Collision Shape</key>
                <dict>
                    <key>id</key>
                    <string>4787</string>
                    <key>className</key>
                    <string>PTModelPolygon</string>
                    <key>Name</key>
                    <dict>
                        <key>value</key>
                        <string></string>
                    </dict>
                    <key>points</key>
                    <array>
                        <string>{-234.000000,-491.000000}</string>
                        <string>{232.000000,-491.000000}</string>
                        <string>{232.000000,499.000000}</string>
                        <string>{-234.000000,499.000000}</string>
                    </array>
                    <key>oneWayCollisionVector</key>
                    <string>{0.000000,0.000000}</string>
                    <key>shapeType</key>
                    <string>1</string>
                </dict>
            </dict>
        </array>
    </dict>
</plist>
